alprina_cli/__init__.py
alprina_cli/acp_server.py
alprina_cli/agent_bridge.py
alprina_cli/agent_coordinator.py
alprina_cli/auth.py
alprina_cli/auth_system.py
alprina_cli/billing.py
alprina_cli/chat.py
alprina_cli/chat_enhanced.py
alprina_cli/chat_ui_enhanced.py
alprina_cli/cli.py
alprina_cli/cli_interactive.py
alprina_cli/config.py
alprina_cli/context_manager.py
alprina_cli/fix_command.py
alprina_cli/history.py
alprina_cli/llm_provider.py
alprina_cli/main_agent.py
alprina_cli/memory_service.py
alprina_cli/mitigation.py
alprina_cli/policy.py
alprina_cli/quick_scanner.py
alprina_cli/quickstart.py
alprina_cli/report_generator.py
alprina_cli/reporting.py
alprina_cli/sbom_command.py
alprina_cli/scanner.py
alprina_cli/security_engine.py
alprina_cli/unified_scanner.py
alprina_cli/workflows.py
alprina_cli/agents/__init__.py
alprina_cli/agents/android_sast.py
alprina_cli/agents/blue_teamer.py
alprina_cli/agents/dfir.py
alprina_cli/agents/guardrails.py
alprina_cli/agents/llm_config.py
alprina_cli/agents/llm_enhancer.py
alprina_cli/agents/llm_security.py
alprina_cli/agents/mail.py
alprina_cli/agents/memory_analysis.py
alprina_cli/agents/network_analyzer.py
alprina_cli/agents/red_teamer.py
alprina_cli/agents/replay_attack.py
alprina_cli/agents/retester.py
alprina_cli/agents/reverse_engineer.py
alprina_cli/agents/subghz_sdr.py
alprina_cli/agents/wifi_security.py
alprina_cli/agents/api_security_sentinel/__init__.py
alprina_cli/agents/api_security_sentinel/api_security_sentinel.py
alprina_cli/agents/cicd_guardian/__init__.py
alprina_cli/agents/cicd_guardian/cicd_guardian.py
alprina_cli/agents/cicd_guardian/cve_database.py
alprina_cli/agents/web3_auditor/__init__.py
alprina_cli/agents/web3_auditor/cross_contract_analyzer.py
alprina_cli/agents/web3_auditor/defi_risk_assessor.py
alprina_cli/agents/web3_auditor/economic_impact_calculator.py
alprina_cli/agents/web3_auditor/gas_optimizer.py
alprina_cli/agents/web3_auditor/mev_detector.py
alprina_cli-0.4.6.dist-info/METADATA
alprina_cli-0.4.6.dist-info/WHEEL
alprina_cli-0.4.6.dist-info/entry_points.txt
alprina_cli-0.4.6.dist-info/RECORD
