Metadata-Version: 2.4
Name: alprina-cli
Version: 0.4.6
Summary: Alprina CLI - AI-powered cybersecurity command-line tool for developers
Project-URL: Homepage, https://alprina.ai
Project-URL: Documentation, https://docs.alprina.ai
Project-URL: Repository, https://github.com/alprina/alprina-cli
Project-URL: Issues, https://github.com/alprina/alprina-cli/issues
Author-email: Malte Wagenbach <malte@alprina.com>
License: Proprietary
Keywords: ai,cli,devops,scanning,security,vulnerability
Classifier: Development Status :: 3 - Alpha
Classifier: Intended Audience :: Developers
Classifier: Programming Language :: Python :: 3.10
Classifier: Programming Language :: Python :: 3.11
Classifier: Programming Language :: Python :: 3.12
Classifier: Topic :: Security
Requires-Python: >=3.10
Requires-Dist: agent-client-protocol>=0.6.2
Requires-Dist: aiofiles>=25.1.0
Requires-Dist: aiohttp>=3.13.2
Requires-Dist: anthropic>=0.39.0
Requires-Dist: click>=8.3.0
Requires-Dist: cryptography>=41.0.0
Requires-Dist: httpx[socks]>=0.28.1
Requires-Dist: jinja2>=3.1.2
Requires-Dist: loguru>=0.7.3
Requires-Dist: openai>=1.0.0
Requires-Dist: pathspec>=0.11.2
Requires-Dist: prompt-toolkit>=3.0.52
Requires-Dist: pydantic>=2.12.3
Requires-Dist: pyjwt>=2.8.0
Requires-Dist: python-dotenv>=1.0.0
Requires-Dist: pyyaml>=6.0.3
Requires-Dist: requests>=2.31.0
Requires-Dist: rich>=14.2.0
Requires-Dist: stripe>=7.0.0
Requires-Dist: tenacity>=9.1.2
Requires-Dist: typer>=0.12.0
Requires-Dist: weasyprint>=60.0
